realgym/__init__.py
realgym-0.0.0.dist-info/METADATA
realgym-0.0.0.dist-info/WHEEL
realgym-0.0.0.dist-info/top_level.txt
realgym-0.0.0.dist-info/RECORD
