Metadata-Version: 2.2
Name: realgym
Version: 0.0.0
Summary: Coming soon
Author-email: Sumeet Motwani <motwani@berkeley.edu>
